tablereader/__init__.py
tablereader/_csv_from_pypy.py
tablereader-1.1.1.dist-info/LICENSE
tablereader-1.1.1.dist-info/METADATA
tablereader-1.1.1.dist-info/WHEEL
tablereader-1.1.1.dist-info/top_level.txt
tablereader-1.1.1.dist-info/RECORD
