Metadata-Version: 2.1
Name: tablereader
Version: 1.1.1
Summary: Unified abstraction for handling xls, xlsx and CSV files in Python
Home-page: https://github.com/jokey2k/tablereader
Author: Markus Ullmann
Author-email: mail@markus-ullmann.de
License: BSD-3
Keywords: encoding,csv,xlsx,xls,xlsm,unicode
Platform: UNKNOWN
Classifier: Development Status :: 5 - Production/Stable
Classifier: Environment :: Plugins
Classifier: Intended Audience :: Developers
Classifier: Intended Audience :: End Users/Desktop
Classifier: Intended Audience :: Financial and Insurance Industry
Classifier: Intended Audience :: Science/Research
Classifier: Intended Audience :: System Administrators
Classifier: License :: OSI Approved :: BSD License
Classifier: Operating System :: OS Independent
Classifier: Programming Language :: Python :: 2.7
Classifier: Programming Language :: Python :: 3.5
Classifier: Programming Language :: Python :: 3.6
Classifier: Programming Language :: Python :: Implementation :: CPython
Classifier: Programming Language :: Python :: Implementation :: PyPy
Classifier: Topic :: Internet :: Log Analysis
Classifier: Topic :: Office/Business :: Financial :: Spreadsheet
Classifier: Topic :: Scientific/Engineering :: Information Analysis
Classifier: Topic :: Software Development :: User Interfaces
Classifier: Topic :: Text Editors :: Text Processing
Classifier: Topic :: Text Processing :: Filters
Classifier: Topic :: Utilities
License-File: LICENSE
Requires-Dist: openpyxl (>3.0.2)
Requires-Dist: six (==1.11.0)
Requires-Dist: xlrd2 (==1.3.4)
